rfc3339.py
rfc3339-6.1.dist-info/LICENSE
rfc3339-6.1.dist-info/METADATA
rfc3339-6.1.dist-info/WHEEL
rfc3339-6.1.dist-info/top_level.txt
rfc3339-6.1.dist-info/RECORD
